Lab1-Counter-master/task2/counter.sv
module counter #(
    parameter WIDTH = 8
)(
    input logic clk,
    input logic rst,
    input logic en,
    output logic [WIDTH-1:0] count
);

always_ff @(posedge clk)
    if(rst) count <= {WIDTH{1'b0}};
    else    count <= count + {{WIDTH-1{1'b0}}, en};

endmodule

Lab1-Counter-master/task1/counter.vcd
$version Generated by VerilatedVcd $end
$timescale 1ps $end
 $scope module TOP $end
  $var wire 1 # clk $end
  $var wire 1 $ rst $end
  $var wire 1 % en $end
  $var wire 8 & count [7:0] $end
  $scope module counter $end
   $var wire 32 ' WIDTH [31:0] $end
   $var wire 1 # clk $end
   $var wire 1 $ rst $end
   $var wire 1 % en $end
   $var wire 8 & count [7:0] $end
  $upscope $end
 $upscope $end
$enddefinitions $end


#0
1#
1$
0%
b00000000 &
b00000000000000000000000000001000 '
#1
0#
#2
1#
#3
0#
#4
1#
#5
0#
#6
1#
0$
#7
0#
#8
1#
#9
0#
#10
1#
#11
0#
#12
1#
1%
#13
0#
#14
1#
b00000001 &
#15
0#
#16
1#
b00000010 &
#17
0#
#18
1#
b00000011 &
#19
0#
#20
1#
b00000100 &
#21
0#
#22
1#
b00000101 &
#23
0#
#24
1#
b00000110 &
#25
0#
#26
1#
b00000111 &
#27
0#
#28
1#
b00001000 &
#29
0#
#30
1#
0%
b00001001 &
